{
  "groups": [
    {
      "groupId": "GROUP_I",
      "groupName": "Sports, Arts, Cultural & Community Activities",
      "maxCounted": 40
    },
    {
      "groupId": "GROUP_II",
      "groupName": "Technical, Professional & Leadership Activities",
      "maxCounted": 40
    },
    {
      "groupId": "GROUP_III",
      "groupName": "Innovation, Research & Advanced Achievements",
      "maxCounted": 40
    }
  ],
  "metadata": {
    "scheme": "KTU 2024 Scheme",
    "version": "1.0",
    "lastUpdated": "2026-01-16",
    "applicableProgrammes": [
      "B.Tech",
      "B.Des",
      "BBA",
      "BCA"
    ]
  },
  "capGroups": [
    {
      "capId": "COMMUNITY_SERVICE_CAP",
      "codes": [
        "1.6",
        "1.7"
      ],
      "maxPoints": 10,
      "description": "Activities 1.6 and 1.7 together are capped at 10 points"
    },
    {
      "capId": "NSS_NCC_CLUSTER",
      "codes": [
        "1.11",
        "1.12",
        "1.13",
        "1.14",
        "1.15",
        "1.16",
        "1.17",
        "1.18",
        "1.19"
      ],
      "maxPoints": 40,
      "description": "Activities 1.11 through 1.19 combined cap at 40 points"
    },
    {
      "capId": "HEALTH_LIFE_SKILLS_CLUSTER",
      "codes": [
        "1.20",
        "1.21"
      ],
      "maxPoints": 10,
      "description": "Activities 1.20 through 1.21 combined cap at 10 points"
    },
    {
      "capId": "TECHNICAL_COMPETITIONS_CLUSTER",
      "codes": [
        "2.1",
        "2.2",
        "2.3",
        "2.4"
      ],
      "maxPoints": 40,
      "description": "Activities 2.1 through 2.4 combined cap at 40 points"
    },
    {
      "capId": "PAPER_PRESENTATION_CLUSTER",
      "codes": [
        "2.6",
        "2.7",
        "2.8",
        "2.9",
        "2.10"
      ],
      "maxPoints": 40,
      "description": "Activities 2.6 through 2.10 combined cap at 40 points"
    },
    {
      "capId": "COLLEGE_MAGAZINE_CLUSTER",
      "codes": [
        "2.20",
        "2.21"
      ],
      "maxPoints": 10,
      "description": "Activities 2.20 through 2.21 combined cap at 10 points"
    },
    {
      "capId": "IV AND PROJECT CLUSTER",
      "codes": [
        "3.1",
        "3.2",
        "3.3"
      ],
      "maxPoints": 20,
      "description": "Activities 3.1 through 3.3 combined cap at 20 points"
    },
    {
      "capId": "INNOVATION_COMPETITIONS_CLUSTER",
      "codes": [
        "3.9",
        "3.10",
        "3.11",
        "3.11b",
        "3.12",
        "3.13"
      ],
      "maxPoints": 40,
      "description": "Activities 3.9 through 3.13 combined cap at 40 points"
    }
  ],
  "categories": [
    {
      "groupId": "GROUP_I",
      "activities": [
        {
          "code": "1.1",
          "rules": [
            "WIN_OVERRIDES_PARTICIPATION",
            "HIGHEST_LEVEL_ONLY"
          ],
          "title": "Sports / Games / Arts – Participation",
          "levels": {
            "state": 10,
            "zonal": 5,
            "college": 1,
            "national": 20,
            "international": 40
          },
          "remarks": "KTU Organized/Approved Events only.",
          "maxPoints": 40,
          "activityId": "SPORTS_PARTICIPATION",
          "calculationType": "LEVEL",
          "documentaryEvidence": "Certificates issued by the hosting college, University, Dean (Student Affairs), College Union Advisor, staff-in-charge, or recognized professional bodies."
        },
        {
          "code": "1.2",
          "rules": [
            "WIN_OVERRIDES_PARTICIPATION",
            "HIGHEST_LEVEL_ONLY"
          ],
          "title": "Sports / Games / Arts – Winners (1st, 2nd, 3rd) – Single Events",
          "levels": {
            "state": 20,
            "zonal": 10,
            "college": 5,
            "national": 40,
            "international": 40
          },
          "remarks": "KTU Organized/Approved Events only.",
          "maxPoints": 40,
          "activityId": "SPORTS_WINNER_SINGLE",
          "calculationType": "LEVEL",
          "documentaryEvidence": "Certificates issued by the hosting college, University, Dean (Student Affairs), College Union Advisor, staff-in-charge, or recognized professional bodies."
        },
        {
          "code": "1.3",
          "rules": [
            "WIN_OVERRIDES_PARTICIPATION",
            "HIGHEST_LEVEL_ONLY"
          ],
          "title": "Sports / Games / Arts – Winners (1st, 2nd, 3rd) – Group Events",
          "levels": {
            "state": 15,
            "zonal": 5,
            "college": 3,
            "national": 30,
            "international": 40
          },
          "remarks": "KTU Organized/Approved Events only.",
          "maxPoints": 40,
          "activityId": "SPORTS_WINNER_GROUP",
          "calculationType": "LEVEL",
          "documentaryEvidence": "Certificates issued by the hosting college, University, Dean (Student Affairs), College Union Advisor, staff-in-charge, or recognized professional bodies."
        },
        {
          "code": "1.4",
          "rules": [
            "MAX_5_PER_MAGAZINE_PER_YEAR"
          ],
          "title": "Publication in College Magazine",
          "points": 5,
          "remarks": "Max 5 points per magazine per academic year. Overall max 20 points.",
          "maxPoints": 20,
          "activityId": "COLLEGE_MAGAZINE_PUB",
          "calculationType": "FIXED",
          "documentaryEvidence": "Copy of the publication or certification from the Editorial Committee."
        },
        {
          "code": "1.5",
          "rules": [
            "DURING_PROGRAMME_ONLY",
            "ONE_TIME"
          ],
          "title": "Four-Wheeler Driving License",
          "points": 5,
          "remarks": "License must be obtained during the original programme duration.",
          "maxPoints": 5,
          "activityId": "FOUR_WHEELER_LICENSE",
          "calculationType": "FIXED",
          "documentaryEvidence": "Copy of the Driving License clearly showing the issue date."
        }
      ],
      "categoryId": "sports_arts_cultural",
      "categoryName": "Sports, Arts & Cultural Activities"
    },
    {
      "groupId": "GROUP_I",
      "activities": [
        {
          "code": "1.6",
          "rules": [],
          "title": "Community Service & Allied Activities (Two Days)",
          "points": 5,
          "remarks": "Special pandemic/disaster volunteer service: 5 Points. Cap shared with 1.7 at 10 points total.",
          "maxPoints": 10,
          "activityId": "COMMUNITY_2DAY",
          "calculationType": "FIXED",
          "documentaryEvidence": "Certificates issued by NSS Programme Officer, Faculty Coordinator, or authorized officials of Government departments, Local Bodies, or NGOs."
        },
        {
          "code": "1.7",
          "rules": [],
          "title": "Community Service & Allied Activities (Up to One Week)",
          "points": 10,
          "remarks": "Special pandemic/disaster volunteer service: 10 Points. Cap shared with 1.6 at 10 points total.",
          "maxPoints": 10,
          "activityId": "COMMUNITY_WEEK",
          "calculationType": "FIXED",
          "documentaryEvidence": "Certificates issued by NSS Programme Officer, Faculty Coordinator, or authorized officials of Government departments, Local Bodies, or NGOs."
        },
        {
          "code": "1.8",
          "rules": [
            "PER_DONATION"
          ],
          "title": "Blood Donation",
          "points": 5,
          "remarks": "5 Points per donation. Maximum 10 points.",
          "maxPoints": 10,
          "activityId": "BLOOD_DONATION",
          "calculationType": "FIXED",
          "documentaryEvidence": "Certificates issued by a Government Blood Bank, Medical College Blood Bank, District Hospital Blood Bank, or any hospital licensed by the State Blood Transfusion Council."
        },
        {
          "code": "1.9",
          "rules": [
            "PER_SEMESTER"
          ],
          "title": "THRIVE Project – Minimum 5 days in a semester",
          "points": 10,
          "remarks": "10 Points per semester. Maximum 20 points.",
          "maxPoints": 20,
          "activityId": "THRIVE_PROJECT",
          "calculationType": "FIXED",
          "documentaryEvidence": "Certificate from the THRIVE programme authority."
        },
        {
          "code": "1.10",
          "rules": [
            "ONE_TIME"
          ],
          "title": "Tree Planting by Students",
          "points": 5,
          "remarks": "Maximum 5 points.",
          "maxPoints": 5,
          "activityId": "TREE_PLANTING",
          "calculationType": "FIXED",
          "documentaryEvidence": "Tree geo-tagging certificate issued by the University NSS Cell."
        }
      ],
      "categoryId": "community_outreach",
      "categoryName": "Community Outreach & Social Initiatives"
    },
    {
      "groupId": "GROUP_I",
      "activities": [
        {
          "code": "1.11",
          "rules": [
            "ONE_TIME"
          ],
          "title": "NSS Volunteer – Two years of volunteership as per NSS Manual",
          "points": 30,
          "maxPoints": 30,
          "activityId": "NSS_VOLUNTEER_2YR",
          "calculationType": "FIXED",
          "documentaryEvidence": "NSS Volunteership Certificate issued by the University NSS Cell."
        },
        {
          "code": "1.12",
          "rules": [],
          "title": "University Level Leadership Camps (100 hours camp)",
          "points": 20,
          "maxPoints": 20,
          "activityId": "NSS_LEADERSHIP_CAMP",
          "calculationType": "FIXED",
          "documentaryEvidence": "Certificate issued by the University NSS Cell."
        },
        {
          "code": "1.13",
          "rules": [],
          "title": "Winners in State Level NSS Festival / State NSS Meet / NSS Competitions (1st, 2nd)",
          "points": 15,
          "maxPoints": 15,
          "activityId": "NSS_STATE_WINNER",
          "calculationType": "FIXED",
          "documentaryEvidence": "Certificate issued by the University / State NSS Cell / NCC Directorate."
        },
        {
          "code": "1.14",
          "rules": [],
          "title": "Special Service Certificate or Appreciation – State Government / State NSS Cell / NCC Directorate",
          "points": 15,
          "maxPoints": 15,
          "activityId": "NSS_SPECIAL_SERVICE",
          "calculationType": "FIXED",
          "documentaryEvidence": "Certificate issued by the University / State NSS Cell / NCC Directorate."
        },
        {
          "code": "1.15",
          "rules": [
            "HIGHEST_LEVEL_ONLY"
          ],
          "title": "Recipient of State / National Level Awards",
          "levels": {
            "state award": 15,
            "national award": 25
          },
          "remarks": "State awards – 15 Points; National level awards – 25 Points.",
          "maxPoints": 40,
          "activityId": "NSS_STATE_NATIONAL_AWARD",
          "calculationType": "LEVEL",
          "documentaryEvidence": "Certificate issued by the University / State NSS Cell / NCC Directorate."
        },
        {
          "code": "1.16",
          "rules": [],
          "title": "Attending Approved National Camps / NIC / NYF / Pre-RDC",
          "points": 15,
          "maxPoints": 15,
          "activityId": "NSS_NATIONAL_CAMPS",
          "calculationType": "FIXED",
          "documentaryEvidence": "Certificate issued by the University / State NSS Cell / NCC Directorate."
        },
        {
          "code": "1.17",
          "rules": [],
          "title": "Ten Days Minimum Volunteer Service (50 hours) – State official programme or State NSS/NCC special projects",
          "points": 15,
          "maxPoints": 15,
          "activityId": "NSS_VOLUNTEER_10DAY",
          "calculationType": "FIXED",
          "documentaryEvidence": "Certificate issued by the University / State NSS Cell / NCC Directorate."
        },
        {
          "code": "1.18",
          "rules": [],
          "title": "Participation in Republic Day Camp (RDC) or Independence Day Camp (IDC) or International events approved by NSS/NCC",
          "points": 25,
          "maxPoints": 25,
          "activityId": "NSS_RDC_IDC",
          "calculationType": "FIXED",
          "documentaryEvidence": "Certificate issued by the University / State NSS Cell / NCC Directorate."
        },
        {
          "code": "1.19",
          "rules": [
            "HIGHEST_LEVEL_ONLY"
          ],
          "title": "NCC Certificates",
          "levels": {
            "ncc_b": 20,
            "ncc_c": 30,
            "one_year_parade": 10
          },
          "remarks": "NCC B – 20 Pts; NCC C – 30 Pts; One Year NCC + Minimum Parade – 10 Pts.",
          "maxPoints": 30,
          "activityId": "NCC_CERTIFICATES",
          "calculationType": "LEVEL",
          "documentaryEvidence": "Certificate issued by the University / NCC Directorate."
        }
      ],
      "categoryId": "nss_ncc",
      "categoryName": "NSS / NCC"
    },
    {
      "groupId": "GROUP_I",
      "activities": [
        {
          "code": "1.20",
          "rules": [
            "PER_TRAINING"
          ],
          "title": "Emergency Response, First Aid, CPR & Fire Safety Training (Minimum half-day certified programme)",
          "points": 5,
          "remarks": "5 Points per training programme. Maximum 10 points.",
          "maxPoints": 10,
          "activityId": "FIRST_AID_CPR",
          "calculationType": "FIXED",
          "documentaryEvidence": "Certificates issued by Government organizations, Fire & Rescue Services, approved training agencies, or registered hospitals."
        },
        {
          "code": "1.21",
          "rules": [
            "ONE_TIME"
          ],
          "title": "Basic Swimming Proficiency",
          "points": 5,
          "maxPoints": 5,
          "activityId": "SWIMMING",
          "calculationType": "FIXED",
          "documentaryEvidence": "Certificates issued by Panchayat/Municipality swimming instructors, Kerala State Sports Council coaches, or registered swimming academies."
        }
      ],
      "categoryId": "health_life_skills",
      "categoryName": "Health, Safety & Essential Life Skills"
    },
    {
      "groupId": "GROUP_II",
      "activities": [
        {
          "code": "2.1",
          "rules": [
            "WIN_OVERRIDES_PARTICIPATION",
            "HIGHEST_LEVEL_ONLY"
          ],
          "title": "Tech-Fest – Participation (Organized or Approved by KTU)",
          "levels": {
            "state": 10,
            "zonal": 5,
            "college": 2,
            "national": 20,
            "international": 30
          },
          "maxPoints": 40,
          "activityId": "TECHFEST_PARTICIPATION",
          "calculationType": "LEVEL",
          "documentaryEvidence": "Certificates issued by the Organizing Institution, Staff-in-Charge of the Professional Society Chapter, or College Union Advisor, verified by SFA."
        },
        {
          "code": "2.2",
          "rules": [
            "WIN_OVERRIDES_PARTICIPATION",
            "HIGHEST_LEVEL_ONLY"
          ],
          "title": "Tech-Fest – Winners (Organized or Approved by KTU)",
          "levels": {
            "state": 20,
            "zonal": 10,
            "college": 5,
            "national": 40,
            "international": 40
          },
          "maxPoints": 40,
          "activityId": "TECHFEST_WINNER",
          "calculationType": "LEVEL",
          "documentaryEvidence": "Certificates issued by the Organizing Institution, Staff-in-Charge of the Professional Society Chapter, or College Union Advisor, verified by SFA."
        },
        {
          "code": "2.3",
          "rules": [
            "WIN_OVERRIDES_PARTICIPATION",
            "HIGHEST_LEVEL_ONLY"
          ],
          "title": "Technical Competitions by Professional Societies (IEEE, IET, ASME, SAE, etc.) – Participation",
          "levels": {
            "state": 10,
            "zonal": 5,
            "college": 2,
            "national": 15,
            "international": 20
          },
          "maxPoints": 40,
          "activityId": "PROFSOC_PARTICIPATION",
          "calculationType": "LEVEL",
          "documentaryEvidence": "Certificates issued by the Organizing Institution, verified by the SFA."
        },
        {
          "code": "2.4",
          "rules": [
            "WIN_OVERRIDES_PARTICIPATION",
            "HIGHEST_LEVEL_ONLY"
          ],
          "title": "Technical Competitions by Professional Societies (IEEE, IET, ASME, SAE, etc.) – Winners (1st, 2nd, 3rd)",
          "levels": {
            "state": 15,
            "zonal": 7,
            "college": 3,
            "national": 25,
            "international": 35
          },
          "maxPoints": 40,
          "activityId": "PROFSOC_WINNER",
          "calculationType": "LEVEL",
          "documentaryEvidence": "Certificates issued by the Organizing Institution, verified by the SFA."
        },
        {
          "code": "2.5",
          "rules": [
            "PER_EVENT"
          ],
          "title": "Attending full-time Conferences, Seminars, Webinars, Workshops, STTPs at IITs/IIITs/NITs/Central Universities/NIRF Top 100 (Excluding fest activities like Ragam)",
          "points": 5,
          "remarks": "5 Points per event. Maximum 15 points.",
          "maxPoints": 15,
          "activityId": "CONFERENCE_SEMINAR",
          "calculationType": "FIXED",
          "documentaryEvidence": "Certificates issued by the Organizing Institution, verified by the SFA."
        },
        {
          "code": "2.6",
          "rules": [
            "PER_EVENT"
          ],
          "title": "Poster Presentation – Participation (KTU approved / IITs / IIITs / NITs / Central Universities / NIRF Top 100)",
          "points": 5,
          "maxPoints": 40,
          "activityId": "POSTER_PARTICIPATION",
          "calculationType": "FIXED",
          "documentaryEvidence": "Certificates issued by the Organizing Institution, verified by the SFA."
        },
        {
          "code": "2.7",
          "rules": [
            "PER_EVENT"
          ],
          "title": "Paper Presentation – Participation (KTU / IITs / IIITs / NITs / Central Universities / NIRF Top 100)",
          "points": 10,
          "maxPoints": 40,
          "activityId": "PAPER_PRES_TOPINST_PARTICIPATION",
          "calculationType": "FIXED",
          "documentaryEvidence": "Certificates issued by the Organizing Institution, verified by the SFA."
        },
        {
          "code": "2.8",
          "rules": [
            "WIN_OVERRIDES_PARTICIPATION"
          ],
          "title": "Paper Presentation – Winners (KTU / IITs / IIITs / NITs / Central Universities / NIRF Top 100)",
          "prizes": {
            "first": 20,
            "second_third": 15
          },
          "maxPoints": 40,
          "activityId": "PAPER_PRES_TOPINST_WINNER",
          "calculationType": "PRIZE",
          "documentaryEvidence": "Certificates issued by the Organizing Institution, verified by the SFA."
        },
        {
          "code": "2.9",
          "rules": [
            "PER_EVENT"
          ],
          "title": "Paper Presentation – Participation (KTU Affiliated institutions)",
          "points": 5,
          "maxPoints": 40,
          "activityId": "PAPER_PRES_KTU_PARTICIPATION",
          "calculationType": "FIXED",
          "documentaryEvidence": "Certificates issued by the Organizing Institution, verified by the SFA."
        },
        {
          "code": "2.10",
          "rules": [
            "WIN_OVERRIDES_PARTICIPATION"
          ],
          "title": "Paper Presentation – Winners (KTU Affiliated institutions)",
          "prizes": {
            "first": 10,
            "second_third": 7
          },
          "maxPoints": 40,
          "activityId": "PAPER_PRES_KTU_WINNER",
          "calculationType": "PRIZE",
          "documentaryEvidence": "Certificates issued by the Organizing Institution, verified by the SFA."
        }
      ],
      "categoryId": "technical_competitions",
      "categoryName": "Technical Events, Competitions & Academic Presentations"
    },
    {
      "groupId": "GROUP_II",
      "activities": [
        {
          "code": "2.11",
          "rules": [
            "PER_EVENT_FOR_COORDINATOR"
          ],
          "title": "Membership in Student Professional Societies (IEEE, IET, ASME, SAE, ACM, ASCE, ISA, etc.) – Minimum 2 Academic Years",
          "levels": {
            "member": 5,
            "event_coordinator": 5,
            "executive_committee": 10,
            "secretary_chapter_lead_chair": 15
          },
          "remarks": "Student Coordinator for an event: 5 points per event.",
          "maxPoints": 15,
          "activityId": "PROF_SOCIETY_MEMBERSHIP",
          "calculationType": "ROLE",
          "documentaryEvidence": "Membership certificate or letter from the professional society chapter."
        },
        {
          "code": "2.12",
          "rules": [],
          "title": "College Union Members",
          "levels": {
            "office_bearer": 20,
            "university_union_office_bearer": 30,
            "executive_committee_excl_office_bearer": 15,
            "university_union_member_excl_office_bearer": 25
          },
          "maxPoints": 30,
          "activityId": "COLLEGE_UNION",
          "calculationType": "ROLE",
          "documentaryEvidence": "Certificate from the College Union Advisor."
        },
        {
          "code": "2.13",
          "rules": [
            "PER_ACADEMIC_YEAR_FOR_EXEC",
            "PER_EVENT_FOR_COORDINATOR"
          ],
          "title": "Department Student Association Activities",
          "levels": {
            "event_coordinator": 5,
            "executive_committee_office_bearer": 5
          },
          "remarks": "Exec/Office Bearer – 5 pts/year; Event Coordinator – 5 pts/event.",
          "maxPoints": 10,
          "activityId": "DEPT_STUDENT_ASSOC",
          "calculationType": "ROLE",
          "documentaryEvidence": "Certificate from the HOD."
        },
        {
          "code": "2.14",
          "rules": [
            "PER_ACADEMIC_YEAR",
            "ONE_PER_CLASS"
          ],
          "title": "Class Representatives",
          "points": 5,
          "remarks": "5 Points per Academic Year. 1 Class Representative per class.",
          "maxPoints": 10,
          "activityId": "CLASS_REPRESENTATIVE",
          "calculationType": "FIXED",
          "documentaryEvidence": "Certificate from the SFA."
        },
        {
          "code": "2.15",
          "rules": [
            "MAX_2_COORDINATORS_PER_CLASS"
          ],
          "title": "Industrial Visit Coordinators (Minimum 6 Days)",
          "points": 5,
          "maxPoints": 5,
          "activityId": "INDUSTRIAL_VISIT_COORDINATOR",
          "calculationType": "FIXED",
          "documentaryEvidence": "Certificate from the faculty in charge."
        },
        {
          "code": "2.16",
          "rules": [
            "MAX_2_COORDINATORS_ATLEAST_1_FEMALE"
          ],
          "title": "Placement Cell (Minimum period of one Academic Year)",
          "levels": {
            "coordinator_convenor": 10,
            "executive_committee_member": 5
          },
          "remarks": "Exec Member – 5 pts (one/class); Coordinator/Convenor – 10 pts. Max 2 coordinators, at least 1 female.",
          "maxPoints": 10,
          "activityId": "PLACEMENT_CELL",
          "calculationType": "ROLE",
          "documentaryEvidence": "Certificates issued by the Staff-in-Charge of the CGPU."
        },
        {
          "code": "2.17",
          "rules": [
            "PER_ACADEMIC_YEAR_FOR_EXEC",
            "PER_EVENT_FOR_COORDINATOR"
          ],
          "title": "IEDC Cell (Minimum period of one Academic Year)",
          "levels": {
            "event_coordinator": 5,
            "executive_committee_office_bearer": 5
          },
          "maxPoints": 10,
          "activityId": "IEDC_CELL",
          "calculationType": "ROLE",
          "documentaryEvidence": "Certificates issued by the Staff-in-Charge of the IEDC Cell."
        },
        {
          "code": "2.18",
          "rules": [],
          "title": "YIP – Young Innovators Programme (K-DISC) – Minimum 1 Academic Year",
          "points": 5,
          "remarks": "Student Coordinator: 5 Points.",
          "maxPoints": 10,
          "activityId": "YIP_GRP2",
          "calculationType": "FIXED",
          "documentaryEvidence": "Certificates issued by KDISC or authorized officials of the YIP Programme."
        },
        {
          "code": "2.19",
          "rules": [],
          "title": "STRIDE – Social Technology & Research for Inclusive Design Excellence (K-DISC) – Minimum 1 Academic Year",
          "levels": {
            "membership": 5,
            "leadership_team_role": 10,
            "high_impact_project_l1": 10,
            "high_impact_project_l2": 15,
            "high_impact_project_l5": 20,
            "certified_volunteer_1yr": 5
          },
          "remarks": "Certified Volunteer: 5 Pts; Membership: 5 Pts; Leadership Team: 10 Pts; Project L1/L2/L5: 10/15/20 Pts.",
          "maxPoints": 20,
          "activityId": "STRIDE_GRP2",
          "calculationType": "ROLE",
          "documentaryEvidence": "Certificates issued by KDISC or authorized officials of the STRIDE Programme."
        },
        {
          "code": "2.20",
          "rules": [
            "MAX_8_STUDENTS_PER_YEAR"
          ],
          "title": "College Magazine Editorial Board (Other than the Magazine Editor)",
          "points": 5,
          "maxPoints": 10,
          "activityId": "MAGAZINE_EDITORIAL",
          "calculationType": "FIXED",
          "documentaryEvidence": "Certificate from the staff in charge of the Editorial Committee or from the College Union Advisor."
        },
        {
          "code": "2.21",
          "rules": [
            "PER_ACADEMIC_YEAR"
          ],
          "title": "Hobby Clubs under College Union (Photography, Film, Music, Dance, Literary, Debate, Coding, Nature Clubs, etc.)",
          "levels": {
            "executive_committee_convenor": 5
          },
          "remarks": "Executive Committee Members/Convenors – 5 Points per Academic Year.",
          "maxPoints": 10,
          "activityId": "HOBBY_CLUBS",
          "calculationType": "ROLE",
          "documentaryEvidence": "Certificate from the staff in charge of the Club and from the College Union Advisor."
        }
      ],
      "categoryId": "leadership_management",
      "categoryName": "Leadership & Management"
    },
    {
      "groupId": "GROUP_II",
      "activities": [
        {
          "code": "2.22",
          "rules": [],
          "title": "ICFOSS / FOSS Club Activities – Minimum Period of 1 Academic Year",
          "levels": {
            "ICFOSS Hackathons / FOSS Events": 5,
            "FOSS Club Student Lead / FOSS Coordinator / Ambassador": 10,
            "ICFOSS approved Workshops / Bootcamps (minimum 2 days)": 5,
            "Contribution to Open-Source Projects (validated by ICFOSS)": 10,
            "FOSS Club Member – participated in at least 2 club activities": 5,
            "FOSS Project Development under ICFOSS / internships (min 15 days)": 10
          },
          "maxPoints": 20,
          "activityId": "FOSS_ACTIVITIES",
          "calculationType": "MULTI_OPTION",
          "documentaryEvidence": "Certificates issued by ICFOSS, approved event organizers, or the faculty-in-Charge of the FOSS Club."
        }
      ],
      "categoryId": "foss_opensource",
      "categoryName": "FOSS Activities & Open-Source Contributions"
    },
    {
      "groupId": "GROUP_II",
      "activities": [
        {
          "code": "2.23",
          "rules": [],
          "title": "Short-Term Internship / Clinical Exposure Training (Minimum 2 Weeks or 10 Working Days)",
          "points": 10,
          "maxPoints": 10,
          "activityId": "SHORT_INTERNSHIP",
          "calculationType": "FIXED",
          "documentaryEvidence": "Certificates issued by the organization, company, or institution where the student underwent the internship or clinical exposure."
        }
      ],
      "categoryId": "short_term_internship",
      "categoryName": "Short-Term Internship"
    },
    {
      "groupId": "GROUP_II",
      "activities": [
        {
          "code": "2.24",
          "rules": [
            "DURING_PROGRAMME_ONLY",
            "HIGHEST_SCORE_ONLY"
          ],
          "title": "English Proficiency Certifications (TOEFL, IELTS, PTE, BEC)",
          "levels": {
            "TOEFL_IBT": [
              {
                ">=105": 30
              },
              {
                "95-104": 25
              },
              {
                "80-94": 20
              }
            ],
            "PTE_ACADEMIC": [
              {
                ">=76": 30
              },
              {
                "65-75": 25
              },
              {
                "58-64": 20
              }
            ],
            "BEC_CAMBRIDGE": [
              {
                "higher_c1": 25
              },
              {
                "vantage_b2": 20
              },
              {
                "preliminary_b1": 15
              }
            ],
            "IELTS_ACADEMIC": [
              {
                ">=7.5": 30
              },
              {
                "7.0": 25
              },
              {
                "6.5": 20
              }
            ]
          },
          "remarks": "Only tests taken during the student's original programme duration will be considered.",
          "maxPoints": 30,
          "activityId": "ENGLISH_PROFICIENCY",
          "calculationType": "SCORE_BAND",
          "documentaryEvidence": "Original score report or downloadable digital scorecard issued by the official testing authority."
        },
        {
          "code": "2.25",
          "rules": [
            "DURING_PROGRAMME_ONLY",
            "HIGHEST_SCORE_ONLY"
          ],
          "title": "Aptitude Proficiency Certifications (GRE, GATE, CAT, GMAT)",
          "levels": {
            "CAT": [
              {
                ">=95%": 30
              },
              {
                "90-94%": 25
              },
              {
                "85-89%": 20
              }
            ],
            "GRE": [
              {
                ">=320": 30
              },
              {
                "310-319": 25
              },
              {
                "300-309": 20
              }
            ],
            "GATE": [
              {
                "AIR<=5000": 30
              },
              {
                "AIR5001-15000": 25
              },
              {
                "Qualified": 20
              }
            ],
            "GMAT": [
              {
                ">=700": 30
              },
              {
                "650-699": 25
              },
              {
                "600-649": 20
              }
            ]
          },
          "maxPoints": 30,
          "activityId": "APTITUDE_PROFICIENCY",
          "calculationType": "SCORE_BAND",
          "documentaryEvidence": "Official scorecard containing score, percentile, test date, and candidate details."
        }
      ],
      "categoryId": "proficiency_certifications",
      "categoryName": "Standardized Tests & Proficiency Certifications"
    },
    {
      "groupId": "GROUP_III",
      "activities": [
        {
          "code": "3.1",
          "rules": [],
          "title": "Industrial Visit / Industrial Training Report (S5 or S6) – Minimum 4 industries",
          "points": 5,
          "maxPoints": 20,
          "activityId": "INDUSTRIAL_VISIT_REPORT",
          "calculationType": "FIXED",
          "documentaryEvidence": "Certified by Faculty Coordinators and SFA. Must confirm minimum 4 industries visited with report containing observations, processes, learning outcomes, and photographs."
        },
        {
          "code": "3.2",
          "rules": [
            "MIN_CLASS_STRENGTH_30"
          ],
          "title": "Best Mini Project / Best Project / Best Seminar (from each class)",
          "points": 5,
          "remarks": "Minimum class strength of 30 required.",
          "maxPoints": 5,
          "activityId": "BEST_PROJECT_SEMINAR",
          "calculationType": "FIXED",
          "documentaryEvidence": "Certificate issued by the Coordinator of the Project/Seminar Evaluation Committee, SFA, and HoD."
        },
        {
          "code": "3.3",
          "rules": [],
          "title": "Long-Term Internship – Minimum 3.5 months as per KTU Guidelines",
          "points": 15,
          "maxPoints": 15,
          "activityId": "LONG_TERM_INTERNSHIP",
          "calculationType": "FIXED",
          "documentaryEvidence": "Internship Completion Certificate mentioning start and end dates (minimum 3.5 months)."
        },
        {
          "code": "3.4",
          "rules": [],
          "title": "LEAP – IIT Madras Incubation Cell Skill Development Bootcamps",
          "levels": {
            "Completion of LEAP Bootcamps (LPB01 & LPB02)": 10,
            "Completion of LEAP Courses (LP1XX/LP2XX/LP3XX)": 15,
            "Completion of LEAP Project / Prototype by LEAP Mentor": 20
          },
          "maxPoints": 30,
          "activityId": "LEAP_IIT_MADRAS",
          "calculationType": "MULTI_OPTION",
          "documentaryEvidence": "Official LEAP Certificate issued by IIT Madras Incubation Cell or certified training partners."
        },
        {
          "code": "3.5",
          "rules": [
            "HIGHEST_MILESTONE_ONLY"
          ],
          "title": "YIP – Young Innovators Programme (K-DISC)",
          "levels": {
            "State Level Winner": 35,
            "Idea Submitted (accepted in YIP portal)": 5,
            "Preliminary Winner (shortlisted for District Round)": 10,
            "District Level Winner / Finalist (Selected by District Panel)": 20
          },
          "maxPoints": 35,
          "activityId": "YIP_GRP3",
          "calculationType": "MILESTONE",
          "documentaryEvidence": "Certificates issued by KDISC or authorized officials of the YIP Programme."
        },
        {
          "code": "3.6",
          "rules": [
            "HIGHEST_MILESTONE_ONLY"
          ],
          "title": "STRIDE – Social Technology & Research for Inclusive Design Excellence (K-DISC)",
          "levels": {
            "State Level Winner": 35,
            "Idea Submitted (Phase 1 completed)": 5,
            "Top 100+ Teams (Selected to Phase-2)": 10,
            "Top 30+ Teams (State-Level Finalists, Phase 3)": 20
          },
          "maxPoints": 35,
          "activityId": "STRIDE_GRP3",
          "calculationType": "MILESTONE",
          "documentaryEvidence": "Certificates issued by KDISC or authorized officials of the STRIDE Programme."
        },
        {
          "code": "3.7",
          "rules": [
            "HIGHEST_MILESTONE_ONLY"
          ],
          "title": "GDC AI Workforce Internship Program",
          "maxPoints": 35,
          "activityId": "GDC_AI_INTERNSHIP",
          "milestones": {
            "Learning Track Completed": 15,
            "AI Grading Test Completed": 5,
            "Fellowship Track Coursework Completed": 25,
            "6-Month Internship Completed (GDC Fellow)": 35
          },
          "calculationType": "MILESTONE",
          "documentaryEvidence": "Certificates issued by AICTE, the official program executor, or the National Health Mission (NHM)."
        },
        {
          "code": "3.8",
          "rules": [],
          "title": "ICFOSS – A working FOSS-based solution or innovation certified by ICFOSS",
          "points": 25,
          "maxPoints": 25,
          "activityId": "ICFOSS_INNOVATION",
          "calculationType": "FIXED",
          "documentaryEvidence": "Certificate issued by ICFOSS."
        }
      ],
      "categoryId": "industry_exposure_internships",
      "categoryName": "Industry Exposure, Academic Projects & Internships"
    },
    {
      "groupId": "GROUP_III",
      "activities": [
        {
          "code": "3.9",
          "rules": [],
          "title": "Start-up Company – Legally Registered (MSME, DPIIT, ROC, Kerala Startup Mission, or recognized Government body)",
          "points": 30,
          "maxPoints": 40,
          "activityId": "STARTUP_REGISTERED",
          "calculationType": "FIXED",
          "documentaryEvidence": "Documentary evidence issued by the respective competent authority."
        },
        {
          "code": "3.10",
          "rules": [
            "HIGHEST_MILESTONE_ONLY"
          ],
          "title": "Patents",
          "levels": {
            "Patent Published in Patent Journal": 30,
            "Patent Granted / Approved – legally granted": 40,
            "Patent Filed – Application filed with IPO/WIPO": 20,
            "Patent Licensed – Technology licensed to industry/user": 40
          },
          "maxPoints": 40,
          "activityId": "PATENTS",
          "calculationType": "MILESTONE",
          "documentaryEvidence": "Documentary evidence issued by the respective competent authority (IPO/WIPO)."
        },
        {
          "code": "3.11",
          "rules": [],
          "title": "Prototype Development & Testing – Functional working model validated by the Innovation Cell or approved Government agencies",
          "points": 40,
          "maxPoints": 40,
          "activityId": "PROTOTYPE_DEVELOPMENT",
          "calculationType": "FIXED",
          "documentaryEvidence": "Prototype validation certificate or letter issued by the Innovation Cell / Government-approved innovation agencies."
        },
        {
          "code": "3.11b",
          "rules": [],
          "title": "Innovative Technologies Adopted by Industry – formally adopted/implemented by a reputed industry or organization",
          "points": 40,
          "maxPoints": 40,
          "activityId": "TECH_ADOPTED_BY_INDUSTRY",
          "calculationType": "FIXED",
          "documentaryEvidence": "Official adoption letter / certification / MoU / implementation report issued by the industry or authorized organization."
        },
        {
          "code": "3.12",
          "rules": [],
          "title": "Venture Capital / Angel Funding – Receiving VC or angel investment for a student-developed product or idea",
          "points": 40,
          "maxPoints": 40,
          "activityId": "VENTURE_CAPITAL_FUNDING",
          "calculationType": "FIXED",
          "documentaryEvidence": "Funding agreement, sanction letter, or investment confirmation issued by the angel investor or recognized funding body."
        },
        {
          "code": "3.13",
          "rules": [],
          "title": "Societal Innovations – Solutions addressing community needs implemented through IEDC, local bodies, or approved Government agencies with measurable impact",
          "points": 40,
          "maxPoints": 40,
          "activityId": "SOCIETAL_INNOVATIONS",
          "calculationType": "FIXED",
          "documentaryEvidence": "Validation letter issued by IEDC / Local Bodies / Government Departments / NGOs / Approved agencies confirming implementation and measurable social impact."
        }
      ],
      "categoryId": "innovation_entrepreneurship_ipr",
      "categoryName": "Innovation, Entrepreneurship & Intellectual Property (IPR)"
    },
    {
      "groupId": "GROUP_III",
      "activities": [
        {
          "code": "3.14",
          "rules": [
            "HIGHEST_LEVEL_ONLY"
          ],
          "title": "Research Publication in Reputed Journals",
          "levels": {
            "sci_scie_scopus_q1_q2": 40,
            "sci_scie_scopus_q3_q4": 25
          },
          "maxPoints": 40,
          "activityId": "JOURNAL_PUBLICATION",
          "calculationType": "LEVEL",
          "documentaryEvidence": "Paper copy or Acceptance Letter from the Editor / Editorial Office."
        }
      ],
      "categoryId": "research_publications",
      "categoryName": "Research Publications & Scholarly Output"
    },
    {
      "groupId": "GROUP_III",
      "activities": [
        {
          "code": "3.15",
          "rules": [
            "WIN_OVERRIDES_PARTICIPATION",
            "HIGHEST_PRIZE_ONLY"
          ],
          "title": "National Hackathons (SIH, KAVACH, MoE, MHA, AICTE, Central Government hackathons, etc.)",
          "levels": {
            "first prize": 40,
            "third prize": 30,
            "second prize": 35
          },
          "maxPoints": 40,
          "activityId": "NATIONAL_HACKATHON",
          "calculationType": "PRIZE",
          "documentaryEvidence": "Certificates issued by the Hackathon Organizing Authority."
        },
        {
          "code": "3.16",
          "rules": [
            "HIGHEST_PRIZE_ONLY"
          ],
          "title": "International Hackathons (NASA Space Apps, Microsoft Imagine Cup, Google Solution Challenge, IBM Call for Code, Meta Global Hackathon, etc.)",
          "levels": {
            "first prize": 40,
            "third prize": 30,
            "second prize": 35
          },
          "maxPoints": 40,
          "activityId": "INTERNATIONAL_HACKATHON",
          "calculationType": "PRIZE",
          "documentaryEvidence": "Certificates issued by the Hackathon Organizing Authority."
        }
      ],
      "categoryId": "hackathons",
      "categoryName": "National & International Hackathons"
    },
    {
      "groupId": "GROUP_III",
      "activities": [
        {
          "code": "3.17",
          "rules": [
            "UNIVERSITY_APPROVED_LIST_ONLY",
            "MULTIPLE_COURSES_ALLOWED"
          ],
          "title": "Skilling Certificates (Approved by the University) – SWAYAM/NPTEL, Spoken Tutorial IIT Bombay, KTU-KDISC, and other University-approved courses",
          "remarks": "1 Point per hour. No points for unapproved courses. Approved list published separately by the University.",
          "maxPoints": 40,
          "activityId": "SKILLING_CERTIFICATES",
          "pointsPerHour": 1,
          "calculationType": "HOURS_BASED",
          "documentaryEvidence": "Certificates issued by the respective platform or organization. SFA must verify the course is in the University approved list and duration meets required hours."
        }
      ],
      "categoryId": "skill_development",
      "categoryName": "Skill Development Courses"
    }
  ],
  "globalRules": [
    {
      "ruleId": "WIN_OVERRIDES_PARTICIPATION",
      "description": "If a student wins, only winning points are awarded — not combined with participation."
    },
    {
      "ruleId": "HIGHEST_LEVEL_ONLY",
      "description": "Only the highest event level achieved is counted."
    },
    {
      "ruleId": "DURING_PROGRAMME_ONLY",
      "description": "Only activities completed during the programme period are eligible."
    },
    {
      "ruleId": "ONE_TIME",
      "description": "Points can be claimed only once regardless of repetitions."
    },
    {
      "ruleId": "PER_EVENT",
      "description": "Points awarded per qualifying event, subject to the overall maximum."
    },
    {
      "ruleId": "PER_DONATION",
      "description": "Points awarded per qualifying blood donation."
    },
    {
      "ruleId": "PER_SEMESTER",
      "description": "Points awarded per semester of qualifying participation."
    },
    {
      "ruleId": "PER_ACADEMIC_YEAR",
      "description": "Points awarded per academic year of qualifying participation."
    },
    {
      "ruleId": "PER_TRAINING",
      "description": "Points awarded per qualifying training programme."
    },
    {
      "ruleId": "HIGHEST_MILESTONE_ONLY",
      "description": "Only the highest achieved milestone is counted."
    },
    {
      "ruleId": "HIGHEST_PRIZE_ONLY",
      "description": "Only the highest prize position is counted for a given event."
    },
    {
      "ruleId": "HIGHEST_SCORE_ONLY",
      "description": "Only the highest score/band is used across multiple attempts."
    },
    {
      "ruleId": "UNIVERSITY_APPROVED_LIST_ONLY",
      "description": "No points for courses not in the University approved list."
    },
    {
      "ruleId": "MULTIPLE_COURSES_ALLOWED",
      "description": "Students may complete multiple approved courses to accumulate points."
    },
    {
      "ruleId": "MAX_5_PER_MAGAZINE_PER_YEAR",
      "description": "Maximum 5 points per college magazine per academic year."
    },
    {
      "ruleId": "MAX_2_COORDINATORS_PER_CLASS",
      "description": "Maximum 2 coordinators recognised per class."
    },
    {
      "ruleId": "MAX_2_COORDINATORS_ATLEAST_1_FEMALE",
      "description": "Maximum 2 coordinators; at least one shall be female."
    },
    {
      "ruleId": "MAX_8_STUDENTS_PER_YEAR",
      "description": "Points awarded to a maximum of 8 students per academic year."
    },
    {
      "ruleId": "ONE_PER_CLASS",
      "description": "Only one student per class is eligible per year."
    },
    {
      "ruleId": "MIN_CLASS_STRENGTH_30",
      "description": "Minimum class strength of 30 students required."
    },
    {
      "ruleId": "PER_EVENT_FOR_COORDINATOR",
      "description": "5 points per event coordinated, subject to overall cap."
    },
    {
      "ruleId": "PER_ACADEMIC_YEAR_FOR_EXEC",
      "description": "Points for executive/office-bearer roles awarded per academic year."
    }
  ],
  "studentCategories": {
    "pwd": {
      "perGroupMin": 20,
      "totalRequired": 60,
      "creditsRequired": 3
    },
    "regular": {
      "perGroupMin": 40,
      "totalRequired": 120,
      "creditsRequired": 3
    },
    "lateralEntry": {
      "perGroupMin": 30,
      "totalRequired": 90,
      "creditsRequired": 3
    }
  }
}
